mycliapp/__init__.py
mycliapp/main.py
mycliapper2-0.17.dist-info/METADATA
mycliapper2-0.17.dist-info/WHEEL
mycliapper2-0.17.dist-info/entry_points.txt
mycliapper2-0.17.dist-info/top_level.txt
mycliapper2-0.17.dist-info/RECORD
