Metadata-Version: 2.1
Name: mycliapper2
Version: 0.17
Summary: UNKNOWN
Home-page: UNKNOWN
License: UNKNOWN
Platform: UNKNOWN
Requires-Dist: apache-airflow
Requires-Dist: click
Requires-Dist: databricks-sql-connector
Requires-Dist: datetime
Requires-Dist: pytz
Requires-Dist: requests
Requires-Dist: typing
